{
  "productTypeName": "Cards",
  "rarityName": "Common",
  "sealed": false,
  "productName": "Corphish",
  "setId": 2071,
  "setCode": "SM04",
  "productId": 149045,
  "setName": "SM - Crimson Invasion",
  "productLineId": 3,
  "productStatusId": 1,
  "productLineName": "Pokemon",
  "skus": [
    {
      "sku": 3527411,
      "condition": "Near Mint",
      "variant": "Normal",
      "language": "English"
    },
    {
      "sku": 3527412,
      "condition": "Lightly Played",
      "variant": "Normal",
      "language": "English"
    },
    {
      "sku": 3527413,
      "condition": "Moderately Played",
      "variant": "Normal",
      "language": "English"
    },
    {
      "sku": 3527414,
      "condition": "Heavily Played",
      "variant": "Normal",
      "language": "English"
    },
    {
      "sku": 3527415,
      "condition": "Damaged",
      "variant": "Normal",
      "language": "English"
    },
    {
      "sku": 3527416,
      "condition": "Near Mint",
      "variant": "Reverse Holofoil",
      "language": "English"
    },
    {
      "sku": 3527417,
      "condition": "Lightly Played",
      "variant": "Reverse Holofoil",
      "language": "English"
    },
    {
      "sku": 3527418,
      "condition": "Moderately Played",
      "variant": "Reverse Holofoil",
      "language": "English"
    },
    {
      "sku": 3527419,
      "condition": "Heavily Played",
      "variant": "Reverse Holofoil",
      "language": "English"
    },
    {
      "sku": 3527420,
      "condition": "Damaged",
      "variant": "Reverse Holofoil",
      "language": "English"
    }
  ]
}