{
  "productTypeName": "Cards",
  "rarityName": "Ultra Rare",
  "sealed": false,
  "productName": "Rockruff",
  "setId": 17674,
  "setCode": "SWSH12: TG",
  "productId": 452021,
  "setName": "SWSH12: Silver Tempest Trainer Gallery",
  "productLineId": 3,
  "productStatusId": 1,
  "productLineName": "Pokemon",
  "skus": [
    {
      "sku": 6679733,
      "condition": "Near Mint",
      "variant": "Holofoil",
      "language": "English"
    },
    {
      "sku": 6679734,
      "condition": "Lightly Played",
      "variant": "Holofoil",
      "language": "English"
    },
    {
      "sku": 6679735,
      "condition": "Moderately Played",
      "variant": "Holofoil",
      "language": "English"
    },
    {
      "sku": 6679736,
      "condition": "Heavily Played",
      "variant": "Holofoil",
      "language": "English"
    },
    {
      "sku": 6679737,
      "condition": "Damaged",
      "variant": "Holofoil",
      "language": "English"
    }
  ]
}