{
  "productTypeName": "Cards",
  "rarityName": "Common",
  "sealed": false,
  "productName": "Basic Psychic Energy",
  "setId": 23529,
  "setCode": "SFA",
  "productId": 562157,
  "setName": "SV: Shrouded Fable",
  "productLineId": 3,
  "productStatusId": 1,
  "productLineName": "Pokemon",
  "skus": [
    {
      "sku": 8085399,
      "condition": "Near Mint",
      "variant": "Reverse Holofoil",
      "language": "English"
    },
    {
      "sku": 8085400,
      "condition": "Lightly Played",
      "variant": "Reverse Holofoil",
      "language": "English"
    },
    {
      "sku": 8085401,
      "condition": "Moderately Played",
      "variant": "Reverse Holofoil",
      "language": "English"
    },
    {
      "sku": 8085402,
      "condition": "Heavily Played",
      "variant": "Reverse Holofoil",
      "language": "English"
    },
    {
      "sku": 8085403,
      "condition": "Damaged",
      "variant": "Reverse Holofoil",
      "language": "English"
    }
  ]
}