{
  "productTypeName": "Cards",
  "rarityName": "Holo Rare",
  "sealed": false,
  "productName": "Dark Typhlosion",
  "setId": 1444,
  "setCode": "N4",
  "productId": 84659,
  "setName": "Neo Destiny",
  "productLineId": 3,
  "productStatusId": 1,
  "productLineName": "Pokemon",
  "skus": [
    {
      "sku": 2897187,
      "condition": "Near Mint",
      "variant": "1st Edition Holofoil",
      "language": "English"
    },
    {
      "sku": 2897188,
      "condition": "Lightly Played",
      "variant": "1st Edition Holofoil",
      "language": "English"
    },
    {
      "sku": 2897189,
      "condition": "Moderately Played",
      "variant": "1st Edition Holofoil",
      "language": "English"
    },
    {
      "sku": 2897190,
      "condition": "Heavily Played",
      "variant": "1st Edition Holofoil",
      "language": "English"
    },
    {
      "sku": 2897191,
      "condition": "Damaged",
      "variant": "1st Edition Holofoil",
      "language": "English"
    },
    {
      "sku": 2897182,
      "condition": "Near Mint",
      "variant": "Unlimited Holofoil",
      "language": "English"
    },
    {
      "sku": 2897183,
      "condition": "Lightly Played",
      "variant": "Unlimited Holofoil",
      "language": "English"
    },
    {
      "sku": 2897184,
      "condition": "Moderately Played",
      "variant": "Unlimited Holofoil",
      "language": "English"
    },
    {
      "sku": 2897185,
      "condition": "Heavily Played",
      "variant": "Unlimited Holofoil",
      "language": "English"
    },
    {
      "sku": 2897186,
      "condition": "Damaged",
      "variant": "Unlimited Holofoil",
      "language": "English"
    }
  ]
}