{
  "productTypeName": "Cards",
  "rarityName": "Common",
  "sealed": false,
  "productName": "Machop (#28)",
  "setId": 1536,
  "setCode": "PR",
  "productId": 98364,
  "setName": "XY Trainer Kit: Latias & Latios",
  "productLineId": 3,
  "productStatusId": 1,
  "productLineName": "Pokemon",
  "skus": [
    {
      "sku": 2875584,
      "condition": "Near Mint",
      "variant": "Normal",
      "language": "English"
    },
    {
      "sku": 2875585,
      "condition": "Lightly Played",
      "variant": "Normal",
      "language": "English"
    },
    {
      "sku": 2875586,
      "condition": "Moderately Played",
      "variant": "Normal",
      "language": "English"
    },
    {
      "sku": 2875587,
      "condition": "Heavily Played",
      "variant": "Normal",
      "language": "English"
    },
    {
      "sku": 2875588,
      "condition": "Damaged",
      "variant": "Normal",
      "language": "English"
    }
  ]
}