{
  "productTypeName": "Cards",
  "rarityName": "Common",
  "sealed": false,
  "productName": "Chinchou (068)",
  "setId": 2585,
  "setCode": "SWSH01",
  "productId": 208367,
  "setName": "SWSH01: Sword & Shield Base Set",
  "productLineId": 3,
  "productStatusId": 1,
  "productLineName": "Pokemon",
  "skus": [
    {
      "sku": 4336541,
      "condition": "Near Mint",
      "variant": "Normal",
      "language": "English"
    },
    {
      "sku": 4336542,
      "condition": "Lightly Played",
      "variant": "Normal",
      "language": "English"
    },
    {
      "sku": 4336543,
      "condition": "Moderately Played",
      "variant": "Normal",
      "language": "English"
    },
    {
      "sku": 4336544,
      "condition": "Heavily Played",
      "variant": "Normal",
      "language": "English"
    },
    {
      "sku": 4336545,
      "condition": "Damaged",
      "variant": "Normal",
      "language": "English"
    },
    {
      "sku": 4336546,
      "condition": "Near Mint",
      "variant": "Reverse Holofoil",
      "language": "English"
    },
    {
      "sku": 4336547,
      "condition": "Lightly Played",
      "variant": "Reverse Holofoil",
      "language": "English"
    },
    {
      "sku": 4336548,
      "condition": "Moderately Played",
      "variant": "Reverse Holofoil",
      "language": "English"
    },
    {
      "sku": 4336549,
      "condition": "Heavily Played",
      "variant": "Reverse Holofoil",
      "language": "English"
    },
    {
      "sku": 4336550,
      "condition": "Damaged",
      "variant": "Reverse Holofoil",
      "language": "English"
    }
  ]
}