{
  "productTypeName": "Cards",
  "rarityName": "Promo",
  "sealed": false,
  "productName": "Cobalion - 84/101 (Cosmos Holo)",
  "setId": 2289,
  "setCode": "BLE",
  "productId": 227474,
  "setName": "Blister Exclusives",
  "productLineId": 3,
  "productStatusId": 1,
  "productLineName": "Pokemon",
  "skus": [
    {
      "sku": 4678877,
      "condition": "Near Mint",
      "variant": "Holofoil",
      "language": "English"
    },
    {
      "sku": 4678878,
      "condition": "Lightly Played",
      "variant": "Holofoil",
      "language": "English"
    },
    {
      "sku": 4678879,
      "condition": "Moderately Played",
      "variant": "Holofoil",
      "language": "English"
    },
    {
      "sku": 4678880,
      "condition": "Heavily Played",
      "variant": "Holofoil",
      "language": "English"
    },
    {
      "sku": 4678881,
      "condition": "Damaged",
      "variant": "Holofoil",
      "language": "English"
    }
  ]
}