{
  "productTypeName": "Cards",
  "rarityName": "Holo Rare",
  "sealed": false,
  "productName": "Cherrim",
  "setId": 2765,
  "setCode": "SWSH05",
  "productId": 234054,
  "setName": "SWSH05: Battle Styles",
  "productLineId": 3,
  "productStatusId": 1,
  "productLineName": "Pokemon",
  "skus": [
    {
      "sku": 4830487,
      "condition": "Near Mint",
      "variant": "Holofoil",
      "language": "English"
    },
    {
      "sku": 4830488,
      "condition": "Lightly Played",
      "variant": "Holofoil",
      "language": "English"
    },
    {
      "sku": 4830489,
      "condition": "Moderately Played",
      "variant": "Holofoil",
      "language": "English"
    },
    {
      "sku": 4830490,
      "condition": "Heavily Played",
      "variant": "Holofoil",
      "language": "English"
    },
    {
      "sku": 4830491,
      "condition": "Damaged",
      "variant": "Holofoil",
      "language": "English"
    },
    {
      "sku": 4816689,
      "condition": "Near Mint",
      "variant": "Reverse Holofoil",
      "language": "English"
    },
    {
      "sku": 4816690,
      "condition": "Lightly Played",
      "variant": "Reverse Holofoil",
      "language": "English"
    },
    {
      "sku": 4816691,
      "condition": "Moderately Played",
      "variant": "Reverse Holofoil",
      "language": "English"
    },
    {
      "sku": 4816692,
      "condition": "Heavily Played",
      "variant": "Reverse Holofoil",
      "language": "English"
    },
    {
      "sku": 4816693,
      "condition": "Damaged",
      "variant": "Reverse Holofoil",
      "language": "English"
    }
  ]
}