{
  "productTypeName": "Cards",
  "rarityName": "Holo Rare",
  "sealed": false,
  "productName": "Alakazam",
  "setId": 604,
  "setCode": "BS",
  "productId": 42346,
  "setName": "Base Set",
  "productLineId": 3,
  "productStatusId": 1,
  "productLineName": "Pokemon",
  "skus": [
    {
      "sku": 2999637,
      "condition": "Near Mint",
      "variant": "Holofoil",
      "language": "English"
    },
    {
      "sku": 2999638,
      "condition": "Lightly Played",
      "variant": "Holofoil",
      "language": "English"
    },
    {
      "sku": 2999639,
      "condition": "Moderately Played",
      "variant": "Holofoil",
      "language": "English"
    },
    {
      "sku": 2999640,
      "condition": "Heavily Played",
      "variant": "Holofoil",
      "language": "English"
    },
    {
      "sku": 2999641,
      "condition": "Damaged",
      "variant": "Holofoil",
      "language": "English"
    },
    {
      "sku": 7317005,
      "condition": "Near Mint",
      "variant": "1st Edition Holofoil",
      "language": "English"
    },
    {
      "sku": 7317006,
      "condition": "Lightly Played",
      "variant": "1st Edition Holofoil",
      "language": "English"
    },
    {
      "sku": 7317007,
      "condition": "Moderately Played",
      "variant": "1st Edition Holofoil",
      "language": "English"
    },
    {
      "sku": 7317008,
      "condition": "Heavily Played",
      "variant": "1st Edition Holofoil",
      "language": "English"
    },
    {
      "sku": 7317009,
      "condition": "Damaged",
      "variant": "1st Edition Holofoil",
      "language": "English"
    }
  ]
}