{
  "productTypeName": "Cards",
  "rarityName": "Holo Rare",
  "sealed": false,
  "productName": "Charizard (Delta Species)",
  "setId": 1395,
  "setCode": "CG",
  "productId": 84195,
  "setName": "Crystal Guardians",
  "productLineId": 3,
  "productStatusId": 1,
  "productLineName": "Pokemon",
  "skus": [
    {
      "sku": 1264183,
      "condition": "Near Mint",
      "variant": "Holofoil",
      "language": "English"
    },
    {
      "sku": 1264184,
      "condition": "Lightly Played",
      "variant": "Holofoil",
      "language": "English"
    },
    {
      "sku": 1264185,
      "condition": "Moderately Played",
      "variant": "Holofoil",
      "language": "English"
    },
    {
      "sku": 1264186,
      "condition": "Heavily Played",
      "variant": "Holofoil",
      "language": "English"
    },
    {
      "sku": 1264187,
      "condition": "Damaged",
      "variant": "Holofoil",
      "language": "English"
    },
    {
      "sku": 1264178,
      "condition": "Near Mint",
      "variant": "Reverse Holofoil",
      "language": "English"
    },
    {
      "sku": 1264179,
      "condition": "Lightly Played",
      "variant": "Reverse Holofoil",
      "language": "English"
    },
    {
      "sku": 1264180,
      "condition": "Moderately Played",
      "variant": "Reverse Holofoil",
      "language": "English"
    },
    {
      "sku": 1264181,
      "condition": "Heavily Played",
      "variant": "Reverse Holofoil",
      "language": "English"
    },
    {
      "sku": 1264182,
      "condition": "Damaged",
      "variant": "Reverse Holofoil",
      "language": "English"
    }
  ]
}