{
  "productTypeName": "Cards",
  "rarityName": "Uncommon",
  "sealed": false,
  "productName": "Delcatty",
  "setId": 1392,
  "setCode": "SS",
  "productId": 84736,
  "setName": "Sandstorm",
  "productLineId": 3,
  "productStatusId": 1,
  "productLineName": "Pokemon",
  "skus": [
    {
      "sku": 1190705,
      "condition": "Near Mint",
      "variant": "Normal",
      "language": "English"
    },
    {
      "sku": 1198051,
      "condition": "Lightly Played",
      "variant": "Normal",
      "language": "English"
    },
    {
      "sku": 1205397,
      "condition": "Moderately Played",
      "variant": "Normal",
      "language": "English"
    },
    {
      "sku": 1212743,
      "condition": "Heavily Played",
      "variant": "Normal",
      "language": "English"
    },
    {
      "sku": 1220089,
      "condition": "Damaged",
      "variant": "Normal",
      "language": "English"
    },
    {
      "sku": 2881262,
      "condition": "Near Mint",
      "variant": "Reverse Holofoil",
      "language": "English"
    },
    {
      "sku": 2881263,
      "condition": "Lightly Played",
      "variant": "Reverse Holofoil",
      "language": "English"
    },
    {
      "sku": 2881264,
      "condition": "Moderately Played",
      "variant": "Reverse Holofoil",
      "language": "English"
    },
    {
      "sku": 2881265,
      "condition": "Heavily Played",
      "variant": "Reverse Holofoil",
      "language": "English"
    },
    {
      "sku": 2881266,
      "condition": "Damaged",
      "variant": "Reverse Holofoil",
      "language": "English"
    }
  ]
}