{
  "productTypeName": "Cards",
  "rarityName": "Rare",
  "sealed": false,
  "productName": "Dragonair - 14/97",
  "setId": 1376,
  "setCode": "DR",
  "productId": 84899,
  "setName": "Dragon",
  "productLineId": 3,
  "productStatusId": 1,
  "productLineName": "Pokemon",
  "skus": [
    {
      "sku": 1190868,
      "condition": "Near Mint",
      "variant": "Normal",
      "language": "English"
    },
    {
      "sku": 1198214,
      "condition": "Lightly Played",
      "variant": "Normal",
      "language": "English"
    },
    {
      "sku": 1205560,
      "condition": "Moderately Played",
      "variant": "Normal",
      "language": "English"
    },
    {
      "sku": 1212906,
      "condition": "Heavily Played",
      "variant": "Normal",
      "language": "English"
    },
    {
      "sku": 1220252,
      "condition": "Damaged",
      "variant": "Normal",
      "language": "English"
    },
    {
      "sku": 2876799,
      "condition": "Near Mint",
      "variant": "Reverse Holofoil",
      "language": "English"
    },
    {
      "sku": 2876800,
      "condition": "Lightly Played",
      "variant": "Reverse Holofoil",
      "language": "English"
    },
    {
      "sku": 2876801,
      "condition": "Moderately Played",
      "variant": "Reverse Holofoil",
      "language": "English"
    },
    {
      "sku": 2876802,
      "condition": "Heavily Played",
      "variant": "Reverse Holofoil",
      "language": "English"
    },
    {
      "sku": 2876803,
      "condition": "Damaged",
      "variant": "Reverse Holofoil",
      "language": "English"
    }
  ]
}