{
  "productTypeName": "Cards",
  "rarityName": "Uncommon",
  "sealed": false,
  "productName": "Hippopotas",
  "setId": 1384,
  "setCode": "SV",
  "productId": 86081,
  "setName": "Supreme Victors",
  "productLineId": 3,
  "productStatusId": 1,
  "productLineName": "Pokemon",
  "skus": [
    {
      "sku": 1192050,
      "condition": "Near Mint",
      "variant": "Normal",
      "language": "English"
    },
    {
      "sku": 1199396,
      "condition": "Lightly Played",
      "variant": "Normal",
      "language": "English"
    },
    {
      "sku": 1206742,
      "condition": "Moderately Played",
      "variant": "Normal",
      "language": "English"
    },
    {
      "sku": 1214088,
      "condition": "Heavily Played",
      "variant": "Normal",
      "language": "English"
    },
    {
      "sku": 1221434,
      "condition": "Damaged",
      "variant": "Normal",
      "language": "English"
    },
    {
      "sku": 2734128,
      "condition": "Near Mint",
      "variant": "Reverse Holofoil",
      "language": "English"
    },
    {
      "sku": 2734129,
      "condition": "Lightly Played",
      "variant": "Reverse Holofoil",
      "language": "English"
    },
    {
      "sku": 2734130,
      "condition": "Moderately Played",
      "variant": "Reverse Holofoil",
      "language": "English"
    },
    {
      "sku": 2734131,
      "condition": "Heavily Played",
      "variant": "Reverse Holofoil",
      "language": "English"
    },
    {
      "sku": 2734132,
      "condition": "Damaged",
      "variant": "Reverse Holofoil",
      "language": "English"
    }
  ],
  "sellerListable": true
}