{
  "productTypeName": "Cards",
  "rarityName": "Holo Rare",
  "sealed": false,
  "productName": "Manectric",
  "setId": 1406,
  "setCode": "PL",
  "productId": 87162,
  "setName": "Platinum",
  "productLineId": 3,
  "productStatusId": 1,
  "productLineName": "Pokemon",
  "skus": [
    {
      "sku": 1249783,
      "condition": "Near Mint",
      "variant": "Holofoil",
      "language": "English"
    },
    {
      "sku": 1249784,
      "condition": "Lightly Played",
      "variant": "Holofoil",
      "language": "English"
    },
    {
      "sku": 1249785,
      "condition": "Moderately Played",
      "variant": "Holofoil",
      "language": "English"
    },
    {
      "sku": 1249786,
      "condition": "Heavily Played",
      "variant": "Holofoil",
      "language": "English"
    },
    {
      "sku": 1249787,
      "condition": "Damaged",
      "variant": "Holofoil",
      "language": "English"
    },
    {
      "sku": 1249778,
      "condition": "Near Mint",
      "variant": "Reverse Holofoil",
      "language": "English"
    },
    {
      "sku": 1249779,
      "condition": "Lightly Played",
      "variant": "Reverse Holofoil",
      "language": "English"
    },
    {
      "sku": 1249780,
      "condition": "Moderately Played",
      "variant": "Reverse Holofoil",
      "language": "English"
    },
    {
      "sku": 1249781,
      "condition": "Heavily Played",
      "variant": "Reverse Holofoil",
      "language": "English"
    },
    {
      "sku": 1249782,
      "condition": "Damaged",
      "variant": "Reverse Holofoil",
      "language": "English"
    }
  ],
  "sellerListable": true
}